video_analyzer/__init__.py
video_analyzer/analyzer.py
video_analyzer/audio_processor.py
video_analyzer/cli.py
video_analyzer/config.py
video_analyzer/frame.py
video_analyzer/prompt.py
video_analyzer/clients/__init__.py
video_analyzer/clients/generic_openai_api.py
video_analyzer/clients/llm_client.py
video_analyzer/clients/ollama.py
video_analyzer/config/default_config.json
video_analyzer/prompts/frame_analysis/describe.txt
video_analyzer/prompts/frame_analysis/frame_analysis.txt
video_analyzer-0.1.1.dist-info/LICENSE
video_analyzer-0.1.1.dist-info/METADATA
video_analyzer-0.1.1.dist-info/WHEEL
video_analyzer-0.1.1.dist-info/entry_points.txt
video_analyzer-0.1.1.dist-info/top_level.txt
video_analyzer-0.1.1.dist-info/RECORD
