Metadata-Version: 2.2
Name: video-analyzer
Version: 0.1.1
Summary: A tool for analyzing videos using Vision models
Author: Jesse White
Requires-Python: >=3.8
License-File: LICENSE
Requires-Dist: opencv-python>=4.8.0
Requires-Dist: numpy>=1.24.0
Requires-Dist: torch>=2.0.0
Requires-Dist: openai-whisper>=20231117
Requires-Dist: requests>=2.31.0
Requires-Dist: Pillow>=10.0.0
Requires-Dist: pydub>=0.25.1
Requires-Dist: faster-whisper>=0.6.0
Dynamic: author
Dynamic: description
Dynamic: description-content-type
Dynamic: requires-dist
Dynamic: requires-python
Dynamic: summary
